clairvoyance2/__init__.py
clairvoyance2/components/__init__.py
clairvoyance2/components/torch/__init__.py
clairvoyance2/components/torch/common.py
clairvoyance2/components/torch/ffnn.py
clairvoyance2/components/torch/gradient_reversal.py
clairvoyance2/components/torch/grud.py
clairvoyance2/components/torch/interfaces.py
clairvoyance2/components/torch/rnn.py
clairvoyance2/components/torch/synctwin_models.py
clairvoyance2/components/torch/synctwin_train_utils.py
clairvoyance2/data/__init__.py
clairvoyance2/data/_utils.py
clairvoyance2/data/constants.py
clairvoyance2/data/dataformat.py
clairvoyance2/data/dataformat_base.py
clairvoyance2/data/dataset.py
clairvoyance2/data/df_constraints.py
clairvoyance2/data/feature.py
clairvoyance2/data/has_features_mixin.py
clairvoyance2/data/has_missing_mixin.py
clairvoyance2/data/internal_utils.py
clairvoyance2/data/to_tensor_like_mixin.py
clairvoyance2/data/update_from.py
clairvoyance2/data/utils/__init__.py
clairvoyance2/data/utils/common.py
clairvoyance2/data/utils/counterfactual_utils.py
clairvoyance2/data/utils/split_time_series.py
clairvoyance2/data/utils/time_index_utils.py
clairvoyance2/datasets/__init__.py
clairvoyance2/datasets/dataset_retriever.py
clairvoyance2/datasets/download.py
clairvoyance2/datasets/dummy.py
clairvoyance2/datasets/uci.py
clairvoyance2/datasets/simulated/__init__.py
clairvoyance2/datasets/simulated/_simple_pkpd.py
clairvoyance2/datasets/simulated/simple_pkpd.py
clairvoyance2/imputation/__init__.py
clairvoyance2/imputation/default_imputer.py
clairvoyance2/interface/__init__.py
clairvoyance2/interface/horizon.py
clairvoyance2/interface/model.py
clairvoyance2/interface/requirements.py
clairvoyance2/interface/saving.py
clairvoyance2/metrics/__init__.py
clairvoyance2/metrics/metric.py
clairvoyance2/metrics/time_series_metrics.py
clairvoyance2/prediction/__init__.py
clairvoyance2/prediction/recurrent.py
clairvoyance2/prediction/seq2seq.py
clairvoyance2/preprocessing/__init__.py
clairvoyance2-0.0.2.dist-info/LICENSE.txt
clairvoyance2-0.0.2.dist-info/METADATA
clairvoyance2-0.0.2.dist-info/WHEEL
clairvoyance2-0.0.2.dist-info/top_level.txt
clairvoyance2-0.0.2.dist-info/RECORD
