Metadata-Version: 2.1
Name: clairvoyance2
Version: 0.0.2
Summary: clairvoyance2: a Unified Toolkit for Medical Time Series
Home-page: https://www.vanderschaar-lab.com/
Author: Evgeny Saveliev
Author-email: e.s.saveliev@gmail.com
License: MIT
Project-URL: Documentation, https://pyscaffold.org/
Platform: any
Classifier: Development Status :: 4 - Beta
Classifier: Programming Language :: Python
Requires-Python: >=3.7
License-File: LICENSE.txt
Requires-Dist: torch
Requires-Dist: pandas
Requires-Dist: numpy
Requires-Dist: matplotlib
Requires-Dist: scikit-learn
Requires-Dist: scipy
Requires-Dist: unlzw3
Requires-Dist: dotmap
Requires-Dist: typing-extensions
Requires-Dist: importlib-metadata ; python_version < "3.8"
Provides-Extra: testing
Requires-Dist: setuptools ; extra == 'testing'
Requires-Dist: pytest ; extra == 'testing'
Requires-Dist: pytest-cov ; extra == 'testing'
Requires-Dist: jupyter ; extra == 'testing'
Requires-Dist: notebook ; extra == 'testing'
Requires-Dist: bandit ; extra == 'testing'
Requires-Dist: black ; extra == 'testing'
Requires-Dist: black-nb ; extra == 'testing'
Requires-Dist: darglint ; extra == 'testing'
Requires-Dist: doc8 ; extra == 'testing'
Requires-Dist: flake8 ; extra == 'testing'
Requires-Dist: isort ; extra == 'testing'
Requires-Dist: nbconvert ; extra == 'testing'
Requires-Dist: nbformat ; extra == 'testing'
Requires-Dist: pytest-benchmark ; extra == 'testing'
Requires-Dist: pytest-xdist[psutil] ; extra == 'testing'
Requires-Dist: pytest-xprocess ; extra == 'testing'
Requires-Dist: igraph ; extra == 'testing'
Requires-Dist: py ; extra == 'testing'
Requires-Dist: pre-commit ; extra == 'testing'
